picoammeter_pon_2_3/__init__.py
picoammeter_pon_2_3/__main__.py
picoammeter_pon_2_3/backWorking.py
picoammeter_pon_2_3/chart.py
picoammeter_pon_2_3/dataHandler.py
picoammeter_pon_2_3/modbusRTUOverTCP.py
picoammeter_pon_2_3/model.py
picoammeter_pon_2_3/outputData.py
picoammeter_pon_2_3/ui/__init__.py
picoammeter_pon_2_3/ui/dialogConfig.py
picoammeter_pon_2_3/ui/mainWindow.py
picoammeter_pon_2_3/ui/uic/__init__.py
picoammeter_pon_2_3/ui/uic/dialogconfig.ui
picoammeter_pon_2_3/ui/uic/mainwindow.ui
neofti_picoammeter_pon_2_3-0.0.1.dist-info/METADATA
neofti_picoammeter_pon_2_3-0.0.1.dist-info/WHEEL
neofti_picoammeter_pon_2_3-0.0.1.dist-info/entry_points.txt
neofti_picoammeter_pon_2_3-0.0.1.dist-info/top_level.txt
neofti_picoammeter_pon_2_3-0.0.1.dist-info/RECORD
