Metadata-Version: 2.1
Name: neofti-picoammeter-pon-2-3
Version: 0.0.1
Summary: Picoammeter pon-2/3 viewer
Home-page: UNKNOWN
Author: DmitryKorovkin
Author-email: d.korovkin69@gmail.com
License: UNKNOWN
Platform: UNKNOWN
Classifier: Programming Language :: Python :: 3
Classifier: License :: OSI Approved :: MIT License
Classifier: Operating System :: OS Independent
Requires-Dist: pyqtgraph
Requires-Dist: numpy
Requires-Dist: pyqt6
Requires-Dist: pymodbus
